build/lib/build/lib/build/lib/docs/examples/example_circuits.py
build/lib/build/lib/build/lib/docs/examples/example_graph.py
build/lib/build/lib/build/lib/docs/examples/example_results.py
build/lib/build/lib/build/lib/docs/examples/example_solve.py
build/lib/build/lib/build/lib/examples/example_circuits.py
build/lib/build/lib/build/lib/examples/example_graph.py
build/lib/build/lib/build/lib/examples/example_results.py
build/lib/build/lib/build/lib/examples/example_solve.py
build/lib/build/lib/build/lib/graphiq/__init__.py
build/lib/build/lib/build/lib/graphiq/io.py
build/lib/build/lib/build/lib/graphiq/metrics.py
build/lib/build/lib/build/lib/graphiq/state.py
build/lib/build/lib/build/lib/graphiq/backends/__init__.py
build/lib/build/lib/build/lib/graphiq/backends/compiler_base.py
build/lib/build/lib/build/lib/graphiq/backends/lc_equivalence_check.py
build/lib/build/lib/build/lib/graphiq/backends/state_base.py
build/lib/build/lib/build/lib/graphiq/backends/state_rep_conversion.py
build/lib/build/lib/build/lib/graphiq/backends/density_matrix/__init__.py
build/lib/build/lib/build/lib/graphiq/backends/density_matrix/compiler.py
build/lib/build/lib/build/lib/graphiq/backends/density_matrix/functions.py
build/lib/build/lib/build/lib/graphiq/backends/density_matrix/state.py
build/lib/build/lib/build/lib/graphiq/backends/graph/__init__.py
build/lib/build/lib/build/lib/graphiq/backends/graph/functions.py
build/lib/build/lib/build/lib/graphiq/backends/graph/state.py
build/lib/build/lib/build/lib/graphiq/backends/stabilizer/__init__.py
build/lib/build/lib/build/lib/graphiq/backends/stabilizer/clifford_tableau.py
build/lib/build/lib/build/lib/graphiq/backends/stabilizer/compiler.py
build/lib/build/lib/build/lib/graphiq/backends/stabilizer/state.py
build/lib/build/lib/build/lib/graphiq/backends/stabilizer/tableau.py
build/lib/build/lib/build/lib/graphiq/backends/stabilizer/functions/__init__.py
build/lib/build/lib/build/lib/graphiq/backends/stabilizer/functions/clifford.py
graphiq-0.1.1.dist-info/LICENSE.md
graphiq-0.1.1.dist-info/METADATA
graphiq-0.1.1.dist-info/WHEEL
graphiq-0.1.1.dist-info/top_level.txt
graphiq-0.1.1.dist-info/RECORD
