Metadata-Version: 2.1
Name: graphiq
Version: 0.1.1
Summary: GraphiQ is a Python library for the simulation, design, and optimization of quantum photonic circuits.
Author-email: Benjamin MacLellan <benjamin@ki3photonics.com>, Jie Lin <jie.lin@quantumbridgetech.com>, Sohban Ghanbari <sobhan.ghanbari@quantumbridgetech.com>, Luc Robichaud <luc.robichaud@qubridge.io>, Piotr Roztocki <piotr@ki3photonics.com>
License: Apache 2.0
Project-URL: Homepage, https://github.com/graphiq-dev/graphiq
Project-URL: Documentation, https://graphiq.readthedocs.io/en/latest/
Project-URL: Repository, https://github.com/graphiq-dev/graphiq.git
Project-URL: Issues, https://github.com/graphiq-dev/graphiq/issues
Keywords: quantum,photonic,circuit,design
Classifier: Development Status :: 4 - Beta
Classifier: Intended Audience :: Science/Research 
Classifier: Topic :: Scientific/Engineering :: Physics
Classifier: Topic :: Security :: Cryptography
Classifier: Topic :: Scientific/Engineering :: Information Analysis
Classifier: Topic :: Scientific/Engineering :: Information Analysis
Classifier: License :: OSI Approved :: Apache Software License
Classifier: Programming Language :: Python :: 3
Classifier: Programming Language :: Python :: 3.8
Classifier: Programming Language :: Python :: 3.9
Classifier: Programming Language :: Python :: 3.10
Requires-Python: <4,>3.8
License-File: LICENSE.md
Requires-Dist: numpy~=1.24.4
Requires-Dist: networkx~=3.1
Requires-Dist: matplotlib~=3.7.5
Requires-Dist: scipy~=1.10.1
Requires-Dist: tqdm
Requires-Dist: seaborn
Requires-Dist: scipy
Requires-Dist: flask~=2.2.2
Requires-Dist: pandas
Requires-Dist: psutil
Requires-Dist: py-cpuinfo
Requires-Dist: qiskit~=0.38.0
Requires-Dist: pylatexenc
Provides-Extra: all
Requires-Dist: jax; extra == "all"
Requires-Dist: optax; extra == "all"
Requires-Dist: ray; extra == "all"
Provides-Extra: docs
Requires-Dist: pymdown-extensions; extra == "docs"
Requires-Dist: mkdocstrings; extra == "docs"
Requires-Dist: mkdocs-material; extra == "docs"
Requires-Dist: mkdocstrings-python; extra == "docs"
Requires-Dist: mknotebooks; extra == "docs"
Requires-Dist: mkdocs-minify-plugin; extra == "docs"
Requires-Dist: mkdocs-add-number-plugin; extra == "docs"
